setup.py
firestone_interface_test_common/__init__.py
firestone_interface_test_common/db_client.py
firestone_interface_test_common/http_client_base.py
firestone_interface_test_common/http_client_manage.py
firestone_interface_test_common/log.py
firestone_interface_test_common/operate_file.py
firestone_interface_test_common/tools.py
firestone_interface_test_common/valid.py
firestone_interface_test_common/variables.py
firestone_interface_test_common.egg-info/PKG-INFO
firestone_interface_test_common.egg-info/SOURCES.txt
firestone_interface_test_common.egg-info/dependency_links.txt
firestone_interface_test_common.egg-info/top_level.txt